from_smiles_step/__init__.py
from_smiles_step/_version.py
from_smiles_step/from_smiles.py
from_smiles_step/from_smiles_parameters.py
from_smiles_step/from_smiles_step.py
from_smiles_step/tk_from_smiles.py
from_smiles_step/data/references.bib
from_smiles_step-2025.5.14.dist-info/licenses/AUTHORS.rst
from_smiles_step-2025.5.14.dist-info/licenses/LICENSE
from_smiles_step-2025.5.14.dist-info/METADATA
from_smiles_step-2025.5.14.dist-info/WHEEL
from_smiles_step-2025.5.14.dist-info/entry_points.txt
from_smiles_step-2025.5.14.dist-info/top_level.txt
from_smiles_step-2025.5.14.dist-info/RECORD
