Metadata-Version: 2.4
Name: from_smiles_step
Version: 2025.5.14
Summary: A SEAMM plug-in for creating structures from a SMILES string.
Home-page: https://github.com/molssi-seamm/from_smiles_step
Author: Paul Saxe
Author-email: psaxe@molssi.org
License: BSD-3-Clause
Keywords: SEAMM,plug-in,flowchart,SMILES,molecule
Platform: Linux
Platform: Mac OS-X
Platform: Unix
Platform: Windows
Classifier: Development Status :: 5 - Production/Stable
Classifier: Intended Audience :: Science/Research
Classifier: License :: OSI Approved :: BSD License
Classifier: Natural Language :: English
Classifier: Programming Language :: Python :: 3 :: Only
Classifier: Programming Language :: Python :: 3.8
Classifier: Programming Language :: Python :: 3.9
License-File: LICENSE
License-File: AUTHORS.rst
Requires-Dist: seamm
Dynamic: author
Dynamic: author-email
Dynamic: classifier
Dynamic: description
Dynamic: description-content-type
Dynamic: home-page
Dynamic: keywords
Dynamic: license
Dynamic: license-file
Dynamic: platform
Dynamic: requires-dist
Dynamic: summary
